taskiq_matrix/__init__.py
taskiq_matrix/exceptions.py
taskiq_matrix/filters.py
taskiq_matrix/instance.py
taskiq_matrix/lock.py
taskiq_matrix/matrix_broker.py
taskiq_matrix/matrix_queue.py
taskiq_matrix/matrix_result_backend.py
taskiq_matrix/schedulesource.py
taskiq_matrix/tasks.py
taskiq_matrix/utils.py
taskiq_matrix-0.1.0.dist-info/LICENSE
taskiq_matrix-0.1.0.dist-info/METADATA
taskiq_matrix-0.1.0.dist-info/WHEEL
taskiq_matrix-0.1.0.dist-info/RECORD
