Metadata-Version: 2.1
Name: taskiq-matrix
Version: 0.1.0
Summary: 
Author: Mo Balaa
Author-email: balaa@ether.ai
Requires-Python: >=3.10,<4.0
Classifier: Programming Language :: Python :: 3
Classifier: Programming Language :: Python :: 3.10
Classifier: Programming Language :: Python :: 3.11
Classifier: Programming Language :: Python :: 3.12
Provides-Extra: dev
Requires-Dist: docker (>=6.1.3,<7.0.0) ; extra == "dev"
Requires-Dist: fractal-matrix-client (>=0.1.0,<0.2.0)
Requires-Dist: ipython (>=8.17.2,<9.0.0) ; extra == "dev"
Requires-Dist: matrix-nio (>=0.22.1,<0.23.0)
Requires-Dist: pytest (>=7.4.2,<8.0.0) ; extra == "dev"
Requires-Dist: pytest-asyncio (>=0.21.1,<0.22.0) ; extra == "dev"
Requires-Dist: pytest-cov (>=4.1.0,<5.0.0) ; extra == "dev"
Requires-Dist: pytest-mock (>=3.11.1,<4.0.0) ; extra == "dev"
Requires-Dist: taskiq (>=0.10.4,<0.11.0)
